homework 1/SR_latch.v
module SR_latch (
	input S, input R, output Q, output Qbar
);

assign Q = ~ (R | Qbar);
assign Qbar = ~ (S | Q);
//nor(Q, R, Qbar);
//nor(Qbar, S, Q);
	
endmodule

homework 1/D_latch.v
`include "SR_latch.v"

module D_latch (
	input D, input E, output Q, output Qbar
);

wire Dbar = ~D;
and(R, Dbar, E);
and(S, D, E);

SR_latch SRr_latch(.S(S), .R(R), .Q(Q), .Qbar(Qbar));

	
endmodule

homework 1/D_flipflop.v
`include "D_latch.v"

module D_flipflop (
	input D, input E, output Q, output Qbar
);

wire Ebar = ~E;
//D_latch D_latch(.D(D), .E(Ebar), .Q(Q), .Qbar(Qbar));
wire Q2;
wire useless;
D_latch D1(.D(D), .E(Ebar), .Q(Q2), .Qbar(useless));
D_latch D2(.D(Q2), .E(E), .Q(Q), .Qbar(Qbar));
	
endmodule

test_banch1/for D_flipflop/test_bench.v
`timescale 1 ns / 100 ps

module testbench(); /* No inputs, no outputs */

reg D = 1'b1; /* Represents clock, initial value is 0 */
reg E = 1'b0; /* Represents clock, initial value is 1 */

always begin
    #1.34 D = ~D; /* Toggle clock every 1ns */
end

always begin
    #2 E = ~E; /* Toggle clock every 2ns */
end

wire Q; /* For output of tested module */
wire Qbar;

D_flipflop  D_flipflop(.D(D), .E(E), .Q(Q), .Qbar(Qbar)); /* Tested module instance */

initial begin
    $dumpvars;      /* Open for dump of signals */
    $display("Test started...");   /* Write to console */
    #20 $finish;    /* Stop simulation after 10ns */
end

endmodule

test_banch1/for D_flipflop/dump.vcd
$date
	Wed Feb 24 01:43:14 2021
$end
$version
	Icarus Verilog
$end
$timescale
	100ps
$end
$scope module testbench $end
$var wire 1 ! Qbar $end
$var wire 1 " Q $end
$var reg 1 # D $end
$var reg 1 $ E $end
$scope module D_flipflop $end
$var wire 1 # D $end
$var wire 1 $ E $end
$var wire 1 % Ebar $end
$var wire 1 & useless $end
$var wire 1 ! Qbar $end
$var wire 1 ' Q2 $end
$var wire 1 " Q $end
$scope module D1 $end
$var wire 1 # D $end
$var wire 1 ( Dbar $end
$var wire 1 % E $end
$var wire 1 ) R $end
$var wire 1 * S $end
$var wire 1 & Qbar $end
$var wire 1 ' Q $end
$scope module SRr_latch $end
$var wire 1 ' Q $end
$var wire 1 & Qbar $end
$var wire 1 ) R $end
$var wire 1 * S $end
$upscope $end
$upscope $end
$scope module D2 $end
$var wire 1 ' D $end
$var wire 1 + Dbar $end
$var wire 1 $ E $end
$var wire 1 , R $end
$var wire 1 - S $end
$var wire 1 ! Qbar $end
$var wire 1 " Q $end
$scope module SRr_latch $end
$var wire 1 " Q $end
$var wire 1 ! Qbar $end
$var wire 1 , R $end
$var wire 1 - S $end
$upscope $end
$upscope $end
$upscope $end
$upscope $end
$enddefinitions $end
#0
$dumpvars
0-
0,
0+
1*
0)
0(
1'
0&
1%
0$
1#
x"
x!
$end
#13
1&
1+
0'
1)
1(
0*
0#
#20
1!
0"
0)
0%
1,
1$
#26
0(
1#
#39
1(
0#
#40
1)
1%
0,
0$
#52
0+
1'
0&
0)
0(
1*
1#
#60
1"
0!
0*
0%
1-
1$
#65
1(
0#
#78
0(
1#
#80
1*
1%
0-
0$
#91
1&
1+
0'
1)
1(
0*
0#
#100
1!
0"
0)
0%
1,
1$
#104
0(
1#
#117
1(
0#
#120
1)
1%
0,
0$
#130
0+
1'
0&
0)
0(
1*
1#
#140
1"
0!
0*
0%
1-
1$
#143
1(
0#
#156
0(
1#
#160
1*
1%
0-
0$
#169
1&
1+
0'
1)
1(
0*
0#
#180
1!
0"
0)
0%
1,
1$
#182
0(
1#
#195
1(
0#
#200
1)
1%
0,
0$
